replicate_whisper_diarization/__init__.py
replicate_whisper_diarization/diarization.py
replicate_whisper_diarization/language.py
replicate_whisper_diarization/main.py
replicate_whisper_diarization/segmentation.py
replicate_whisper_diarization/webhook.py
replicate_whisper_diarization/whisper.py
replicate_whisper_diarization-0.2.9.dist-info/LICENSE
replicate_whisper_diarization-0.2.9.dist-info/METADATA
replicate_whisper_diarization-0.2.9.dist-info/WHEEL
replicate_whisper_diarization-0.2.9.dist-info/top_level.txt
replicate_whisper_diarization-0.2.9.dist-info/RECORD
