Metadata-Version: 2.2
Name: replicate_whisper_diarization
Version: 0.2.9
Summary: Transcribe and diarize audio files using Replicate models
Author-email: "Collective.ai" <info@collectiveai.io>
License: 
Project-URL: Homepage, https://github.com/collectiveai-team/whisper-diarization
Keywords: feed,reader,tutorial
Classifier: License :: OSI Approved :: MIT License
Classifier: Programming Language :: Python
Classifier: Programming Language :: Python :: 3
Requires-Python: >=3.9
License-File: LICENSE
Requires-Dist: replicate>=0.25.2
Requires-Dist: flask<4,>=3.0.3
